typecode_libmagic_from_sources/__init__.py
typecode_libmagic_from_sources/data/.gitignore
typecode_libmagic_from_sources/data/.keepme
typecode_libmagic_from_sources/data/magic.mgc
typecode_libmagic_from_sources/lib/.gitignore
typecode_libmagic_from_sources/lib/.keepme
typecode_libmagic_from_sources/lib/libmagic.so
typecode_libmagic_from_sources/licenses/libmagic/COPYING
typecode_libmagic_from_sources/licenses/libmagic/ChangeLog
typecode_libmagic_from_sources/licenses/libmagic/README
typecode_libmagic_from_sources-5.39.210212.dist-info/METADATA
typecode_libmagic_from_sources-5.39.210212.dist-info/README.rst
typecode_libmagic_from_sources-5.39.210212.dist-info/WHEEL
typecode_libmagic_from_sources-5.39.210212.dist-info/bsd-new.LICENSE
typecode_libmagic_from_sources-5.39.210212.dist-info/bsd-original.LICENSE
typecode_libmagic_from_sources-5.39.210212.dist-info/bsd-simplified-darwin.LICENSE
typecode_libmagic_from_sources-5.39.210212.dist-info/bsd-simplified.LICENSE
typecode_libmagic_from_sources-5.39.210212.dist-info/entry_points.txt
typecode_libmagic_from_sources-5.39.210212.dist-info/gpl-1.0-plus.LICENSE
typecode_libmagic_from_sources-5.39.210212.dist-info/gpl-1.0.LICENSE
typecode_libmagic_from_sources-5.39.210212.dist-info/isc.LICENSE
typecode_libmagic_from_sources-5.39.210212.dist-info/libmagic.ABOUT
typecode_libmagic_from_sources-5.39.210212.dist-info/libmagic.NOTICE
typecode_libmagic_from_sources-5.39.210212.dist-info/public-domain.LICENSE
typecode_libmagic_from_sources-5.39.210212.dist-info/top_level.txt
typecode_libmagic_from_sources-5.39.210212.dist-info/typecode-libmagic.ABOUT
typecode_libmagic_from_sources-5.39.210212.dist-info/RECORD
